{
  "in house": "家の中",
  "in apartment": "アパートの中",
  "in living room": "リビングルームの中",
  "in bedroom": "寝室の中",
  "in kitchen": "キッチンの中",
  "in garden": "庭の中",
  "in backyard": "裏庭の中",
  "in forest": "森の中",
  "in meadow": "草原の中",
  "in city street": "都市の通りの中",
  "in alley": "路地の中",
  "on fence": "フェンスの上",
  "on wall": "壁の上",
  "on tree": "木の上",
  "on windowsill": "窓辺の上",
  "on sofa": "ソファの上",
  "on bed": "ベッドの上",
  "on chair": "椅子の上",
  "on table": "テーブルの上",
  "on bookshelf": "本棚の上",
  "in cardboard box": "段ボール箱の中",
  "in cat bed": "猫用ベッドの中",
  "in cat tree": "キャットタワーの中",
  "in cat carrier": "キャリーケースの中",
  "in cat house": "猫小屋の中",
  "at night": "夜に",
  "at sunset": "夕暮れ時に",
  "at sunrise": "日の出時に",
  "in rain": "雨の中",
  "in snow": "雪の中",
  "on a race track": "レーストラックで",
  "in a showroom": "ショールームで",
  "on a mountain road": "山道で",
  "in a city street": "都市の通りで",
  "in a parking lot": "駐車場で",
  "on a highway": "高速道路で",
  "in a garage": "ガレージで",
  "in the rain": "雨の中",
  "in the snow": "雪の中",
  "on a beach": "ビーチで",
  "at a motorcycle show": "オートバイショーで",
  "in an urban setting": "都市部で",
  "in a workshop": "ワークショップで",
  "at a dealership": "ディーラーで"
}