{
    "Dark brown hair": "ダークブラウンの髪",
    "ash hair": "アッシュ",
    "black hair": "黒髪",
    "black hair, cloth color is white or gray": "黒髪と白・灰色系の生地",
    "black hair, cloth color is white or gray or black": "黒髪とモノトーンの生地",
    "blonde hair": "金髪",
    "brown hair": "茶髪",
    "colored inner hair": "インナーカラー",
    "copper hair": "艶のある茶髪",
    "jet black hair": "漆黒の髪",
    "jet black hair, cloth color is white or gray": "漆黒の髪と白・灰色系の生地",
    "jet black hair, cloth color is white or gray or black": "漆黒の髪とモノトーンの生地",
    "light brown hair": "明るい茶髪",
    "pink hair, (white inner hair:1.3, cloth color is gray or black: 1.2)": "インナーカラーが白のピンク髪と黒・灰色の服",
    "platinum hair": "プラチナブロンド",
    "red hair, cloth color is white or gray or black": "赤毛とモノトーンの生地",
    "sheer beige hair": "シアーベージュ",
    "two-tone hair": "ツートンカラー"
}
