{
    "anime inviting home": "居心地の良い家",
    "fantasy cozy dwelling": "温かな住まい",
    "magical elegant residence": "エレガントな住居",
    "anime luxurious property": "豪華な物件",
    "fantasy charming abode": "魅力的な住処",
    "magical rustic retreat": "素朴な隠れ家",
    "anime stylish residence": "スタイリッシュな住居",
    "magical idyllic house": "理想的な家",
    "inviting home": "居心地の良い家",
    "cozy dwelling": "温かな住まい",
    "elegant residence": "エレガントな住居",
    "luxurious property": "豪華な物件",
    "charming abode": "魅力的な住処",
    "rustic retreat": "素朴な隠れ家",
    "stylish residence": "スタイリッシュな住居",
    "idyllic house": "理想的な家",
    "picturesque dwelling": "絵のように美しい住まい"
}