{
    "fantasy commercial district": "幻想的な商業地区",
    "magical financial center": "魔法の金融センター",
    "anime historic district": "アニメ風の歴史地区",
    "fantasy cultural quarter": "幻想的な文化地区",
    "magical entertainment area": "魔法のエンターテイメントエリア",
    "anime school district": "アニメ風の学校地区",
    "fantasy government quarter": "幻想的な政府地区",
    "magical embassy district": "魔法の大使館地区",
    "anime shopping area": "アニメ風のショッピングエリア",
    "fantasy industrial zone": "幻想的な工業地帯",
    "magical port area": "魔法の港エリア",
    "anime train station district": "アニメ風の駅前地区",
    "fantasy ethnic quarter": "幻想的な民族地区",
    "international metropolis": "国際的な大都市",
    "financial district": "金融街",
    "historic center": "歴史的中心地",
    "cultural quarter": "文化地区",
    "entertainment district": "娯楽街",
    "university area": "大学地区",
    "government district": "政府機関街",
    "diplomatic quarter": "外交官地区",
    "shopping district": "ショッピング街",
    "industrial zone": "工業地帯",
    "port area": "港湾地区",
    "railway district": "鉄道地区",
    "chinatown": "中華街",
    "little italy": "リトルイタリー",
    "ethnic quarter": "民族地区"
}